dataverse_pooch
