Metadata-Version: 2.1
Name: dataverse-pooch
Version: 0.1.1
Summary: Create pooch registry files from DataVerse repositories
Maintainer-email: Dominic Kempf <ssc@iwr.uni-heidelberg.de>
License: MIT
Classifier: Programming Language :: Python :: 3
Classifier: Operating System :: OS Independent
Classifier: License :: OSI Approved :: MIT License
Requires-Python: >=3.8
License-File: LICENSE.md
